raudio_server/__init__.py
raudio_server/hls.py
raudio_server/pause_req.py
raudio_server/play_req.py
raudio_server/server.py
raudio_server/skip_req.py
raudio_server-0.1.0rc4.dist-info/LICENSE
raudio_server-0.1.0rc4.dist-info/METADATA
raudio_server-0.1.0rc4.dist-info/WHEEL
raudio_server-0.1.0rc4.dist-info/top_level.txt
raudio_server-0.1.0rc4.dist-info/RECORD
