Metadata-Version: 2.1
Name: raudio-server
Version: 0.1.0rc4
Summary: Self-hosted music streaming server
Home-page: https://raudio-project.github.io
Author: Raudio Project
Author-email: ndlug@nd.edu
License: UNKNOWN
Platform: UNKNOWN
Classifier: Programming Language :: Python :: 3
Classifier: License :: OSI Approved :: GNU General Public License v3 (GPLv3)
Requires-Python: >=3.7
License-File: LICENSE
Requires-Dist: ffmpeg-python (==0.2.0)
Requires-Dist: flask (==2.1.1)
Requires-Dist: requests (==2.27.1)
